LICENSE
README.rst
scadi/__init__.py
scadi/__main__.py
scadi/inline.py
scadi/main.py
scadi-0.1.5.dist-info/LICENSE
scadi-0.1.5.dist-info/METADATA
scadi-0.1.5.dist-info/WHEEL
scadi-0.1.5.dist-info/entry_points.txt
scadi-0.1.5.dist-info/RECORD
