Metadata-Version: 2.1
Name: scadi
Version: 0.1.5
Summary: SCAD Inliner: Roll up OpenSCAD includes into the main file for easy sharing.
Home-page: https://nascentmaker.com/py/scadi
License: MIT
Keywords: openscad,inline,minimizer,rollup,scad
Author: Nascent Maker
Author-email: hello@nascentmaker.com
Maintainer: Nascent Maker
Maintainer-email: hello@nascentmaker.com
Requires-Python: >=3.8,<4.0
Classifier: Development Status :: 5 - Production/Stable
Classifier: Environment :: Console
Classifier: Intended Audience :: Developers
Classifier: Intended Audience :: End Users/Desktop
Classifier: License :: OSI Approved :: MIT License
Classifier: Operating System :: OS Independent
Classifier: Programming Language :: Python
Classifier: Programming Language :: Python :: 3
Classifier: Programming Language :: Python :: 3.8
Classifier: Programming Language :: Python :: 3.9
Classifier: Programming Language :: Python :: 3.10
Classifier: Programming Language :: Python :: 3.11
Classifier: Programming Language :: Python :: 3
Classifier: Programming Language :: Python :: 3 :: Only
Classifier: Programming Language :: Python :: 3.10
Classifier: Programming Language :: Python :: 3.8
Classifier: Programming Language :: Python :: 3.9
Classifier: Programming Language :: Python :: Implementation :: CPython
Requires-Dist: cliff (>=3.10,<5.0)
Requires-Dist: platformdirs (>=3.1.1,<4.0.0)
Project-URL: Repository, https://github.com/NascentMaker/scadi
